{
  "keywords": [
    {
      "value": "collision",
      "priority": true
    },
    {
      "value": "liability",
      "priority": true
    },
    {
      "value": "SGI claim",
      "priority": true
    },
    {
      "value": "SAID application",
      "priority": true
    },
    {
      "value": "spousal support",
      "priority": true
    },
    {
      "value": "medical restriction",
      "priority": true
    },
    {
      "value": "settlement",
      "priority": false
    }
  ],
  "entities": [
    {
      "label": "At-Fault Party",
      "value": "Sarah Andersen",
      "priority": true
    },
    {
      "label": "Insurance Regulator",
      "value": "SGI Adjuster",
      "priority": true
    },
    {
      "label": "Medical Proof",
      "value": "Dr. Miller",
      "priority": true
    },
    {
      "label": "Provincial Support",
      "value": "SAID Caseworker",
      "priority": true
    }
  ]
}